README.rst
setup.py
bin/smarty
smarty/__init__.py
smarty/cmd_line_parser.py
smarty/communication_handler.py
smarty.egg-info/PKG-INFO
smarty.egg-info/SOURCES.txt
smarty.egg-info/dependency_links.txt
smarty.egg-info/requires.txt
smarty.egg-info/top_level.txt
smarty.egg-info/zip-safe