Metadata-Version: 1.0
Name: smarty
Version: 0.3.3
Summary: Smart playlist creation for mpd
Home-page: https://github.com/kpj/Smarty
Author: kpj
Author-email: kpjkpjkpjkpjkpjkpj@gmail.com
License: Apache2
Platform: UNKNOWN
